CHANGES
COPYING
MANIFEST.in
README.md
cherrymusic
cherrymusic-tray
cherrymusicd
setup.py
CherryMusic.egg-info/PKG-INFO
CherryMusic.egg-info/SOURCES.txt
CherryMusic.egg-info/dependency_links.txt
CherryMusic.egg-info/requires.txt
CherryMusic.egg-info/top_level.txt
audiotranscode/__init__.py
audiotranscode/test/__init__.py
audiotranscode/test/test_transcode.py
backport/__init__.py
backport/collections/__init__.py
backport/collections/_backported.py
backport/configparser/__init__.py
backport/logging/__init__.py
backport/urllib/__init__.py
backport/urllib/parse/__init__.py
backport/urllib/request/__init__.py
cherrymusicserver/__init__.py
cherrymusicserver/albumartfetcher.py
cherrymusicserver/browsersetup.py
cherrymusicserver/cherrymodel.py
cherrymusicserver/configuration.py
cherrymusicserver/httphandler.py
cherrymusicserver/i18n_client.py
cherrymusicserver/log.py
cherrymusicserver/metainfo.py
cherrymusicserver/pathprovider.py
cherrymusicserver/playlistdb.py
cherrymusicserver/progress.py
cherrymusicserver/resultorder.py
cherrymusicserver/service.py
cherrymusicserver/sqlitecache.py
cherrymusicserver/tweak.py
cherrymusicserver/userdb.py
cherrymusicserver/useroptiondb.py
cherrymusicserver/util.py
cherrymusicserver/api/__init__.py
cherrymusicserver/api/test/__init__.py
cherrymusicserver/api/test/test_v1.py
cherrymusicserver/api/v1/__init__.py
cherrymusicserver/api/v1/jsontools.py
cherrymusicserver/api/v1/models.py
cherrymusicserver/api/v1/resources.py
cherrymusicserver/api/v1/users.py
cherrymusicserver/api/v1/test/__init__.py
cherrymusicserver/api/v1/test/test_models.py
cherrymusicserver/database/__init__.py
cherrymusicserver/database/connect.py
cherrymusicserver/database/sql.py
cherrymusicserver/database/defs/__init__.py
cherrymusicserver/database/defs/cherry.cache/0/create.sql
cherrymusicserver/database/defs/cherry.cache/0/drop.sql
cherrymusicserver/database/defs/cherry.cache/1/after.sql
cherrymusicserver/database/defs/cherry.cache/1/create.sql
cherrymusicserver/database/defs/cherry.cache/1/drop.sql
cherrymusicserver/database/defs/cherry.cache/1/prompt
cherrymusicserver/database/defs/cherry.cache/1/update.sql
