Metadata-Version: 2.1
Name: CherryMusic
Version: 0.41.4
Summary: an mp3 server for your browser
Home-page: http://www.fomori.org/cherrymusic/
Author: Tom Wallroth & Tilman Boerner
Author-email: tomwallroth@gmail.com, tilman.boerner@gmx.net
License: GPLv3
Classifier: Programming Language :: Python
Classifier: Programming Language :: Python :: 2.6
Classifier: Programming Language :: Python :: 2.7
Classifier: Programming Language :: Python :: 3
Classifier: Programming Language :: Python :: 3.2
Classifier: Programming Language :: Python :: 3.3
Classifier: Development Status :: 4 - Beta
Classifier: Environment :: Console
Classifier: Environment :: Web Environment
Classifier: Framework :: CherryPy
Classifier: Intended Audience :: End Users/Desktop
Classifier: Intended Audience :: Developers
Classifier: Intended Audience :: System Administrators
Classifier: License :: OSI Approved :: GNU General Public License v3 (GPLv3)
Classifier: Operating System :: OS Independent
Classifier: Natural Language :: English
Classifier: Topic :: Internet :: WWW/HTTP
Classifier: Topic :: Multimedia
Classifier: Topic :: Multimedia :: Sound/Audio :: Players
License-File: COPYING
